{
  "Actors": [
    {
      "Translate": {
        "X": -0.7500001,
        "Y": 15.0,
        "Z": 12.75
      },
      "Actor name": "TagAreaStart",
      "Actor params": [
        "S104_R001_Start",
        "AreaStartCommon:WalkIn",
        null,
        "",
        0.0,
        0.0
      ],
      "Conditions": []
    },
    {
      "Translate": {
        "X": -0.75,
        "Y": 15.0,
        "Z": 8.25
      },
      "Actor name": "TagAreaStart",
      "Actor params": [
        "S104_R001_WarpBoss",
        "AreaStartCommon:MidBossWarpIn",
        null,
        "",
        0.0,
        0.0
      ],
      "Conditions": []
    },
    {
      "Translate": {
        "X": 17.25,
        "Y": 15.0,
        "Z": -30.75
      },
      "Actor name": "TagAreaStart",
      "Actor params": [
        "S110_R004_Start",
        "AreaStartCommon:TopWallLadderUpIn",
        null,
        "",
        0.0,
        0.0
      ],
      "Conditions": []
    },
    {
      "Translate": {
        "X": 110.25,
        "Y": -12.049999,
        "Z": -0.75
      },
      "Actor name": "TagAreaStart",
      "Actor params": [
        "S110_R006_Start",
        "AreaStartCommon:LadderDown",
        null,
        "Wall"
      ],
      "Conditions": []
    },
    {
      "Translate": {
        "X": -0.75,
        "Y": 15.0,
        "Z": 6.0
      },
      "Actor name": "TagTailorPlayer",
      "Actor params": [
        "S_Dungeon104_001_Effect_00"
      ],
      "Conditions": []
    },
    {
      "Translate": {
        "X": -0.75,
        "Y": 15.0,
        "Z": 6.0
      },
      "Actor name": "MapStatic",
      "Actor params": [
        "S_Dungeon104_001",
        "",
        "",
        0,
        1
      ],
      "Conditions": []
    },
    {
      "Translate": {
        "X": -0.7500001,
        "Y": 15.75,
        "Z": 12.75
      },
      "Actor name": "SensorLevelOpen",
      "Actor params": [
        "Field",
        "Field_Jungle_008",
        "AreaExitCommon:WalkOut",
        0,
        "",
        null,
        0
      ],
      "Conditions": []
    },
    {
      "Translate": {
        "X": -0.75,
        "Y": 15.0,
        "Z": 3.75
      },
      "Actor name": "TreasureBox",
      "Actor params": [
        "true",
        197,
        0,
        0,
        "",
        "",
        1,
        false
      ],
      "Conditions": []
    },
    {
      "Translate": {
        "X": 3.75,
        "Y": 15.0,
        "Z": 0.75
      },
      "Actor name": "Pot",
      "Actor params": [],
      "Conditions": []
    },
    {
      "Translate": {
        "X": 3.75,
        "Y": 15.0,
        "Z": 11.25
      },
      "Actor name": "Pot",
      "Actor params": [],
      "Conditions": []
    },
    {
      "Translate": {
        "X": -5.25,
        "Y": 15.0,
        "Z": 11.25
      },
      "Actor name": "Pot",
      "Actor params": [],
      "Conditions": []
    },
    {
      "Translate": {
        "X": -5.25,
        "Y": 15.0,
        "Z": 0.75
      },
      "Actor name": "Pot",
      "Actor params": [],
      "Conditions": []
    },
    {
      "Translate": {
        "X": 2.25,
        "Y": 15.0,
        "Z": 8.25
      },
      "Actor name": "LampJungle",
      "Actor params": [
        0,
        false
      ],
      "Conditions": [
        [
          null,
          4
        ],
        [
          1,
          2
        ]
      ]
    },
    {
      "Translate": {
        "X": 2.25,
        "Y": 15.0,
        "Z": 3.75
      },
      "Actor name": "LampJungle",
      "Actor params": [
        0,
        false
      ],
      "Conditions": [
        [
          null,
          4
        ],
        [
          1,
          2
        ]
      ]
    },
    {
      "Translate": {
        "X": -3.75,
        "Y": 15.0,
        "Z": 8.25
      },
      "Actor name": "LampJungle",
      "Actor params": [
        0,
        false
      ],
      "Conditions": [
        [
          null,
          4
        ],
        [
          1,
          2
        ]
      ]
    },
    {
      "Translate": {
        "X": -3.75,
        "Y": 15.0,
        "Z": 3.75
      },
      "Actor name": "LampJungle",
      "Actor params": [
        0,
        false
      ],
      "Conditions": [
        [
          null,
          4
        ],
        [
          1,
          2
        ]
      ]
    },
    {
      "Translate": {
        "X": -0.75,
        "Y": 15.0,
        "Z": 6.375
      },
      "Actor name": "EvQuestDoorBalom01",
      "Actor params": [],
      "Conditions": []
    },
    {
      "Translate": {
        "X": -0.75,
        "Y": 15.0,
        "Z": -9.0
      },
      "Actor name": "TagTailorPlayer",
      "Actor params": [
        "S_Dungeon104_002_Effect_00"
      ],
      "Conditions": []
    },
    {
      "Translate": {
        "X": 5.25,
        "Y": 17.25,
        "Z": -5.25
      },
      "Actor name": "TagRoomLocker",
      "Actor params": [
        "",
        "",
        ""
      ],
      "Conditions": [
        [
          0,
          3
        ]
      ]
    },
    {
      "Translate": {
        "X": -0.75,
        "Y": 15.0,
        "Z": -9.0
      },
      "Actor name": "MapStatic",
      "Actor params": [
        "S_Dungeon104_002",
        "",
        "",
        0,
        1
      ],
      "Conditions": []
    },
    {
      "Translate": {
        "X": 3.75,
        "Y": 15.0,
        "Z": -6.75
      },
      "Actor name": "Spark00",
      "Actor params": [
        2,
        0
      ],
      "Conditions": []
    },
    {
      "Translate": {
        "X": -5.25,
        "Y": 15.0,
        "Z": -11.25
      },
      "Actor name": "Spark00",
      "Actor params": [
        2,
        1
      ],
      "Conditions": []
    },
    {
      "Translate": {
        "X": -3.75,
        "Y": 15.0,
        "Z": -6.75
      },
      "Actor name": "LampJungle",
      "Actor params": [
        0,
        false
      ],
      "Conditions": [
        [
          null,
          4
        ],
        [
          1,
          2
        ]
      ]
    },
    {
      "Translate": {
        "X": 2.25,
        "Y": 15.0,
        "Z": -6.75
      },
      "Actor name": "LampJungle",
      "Actor params": [
        0,
        false
      ],
      "Conditions": [
        [
          null,
          4
        ],
        [
          1,
          2
        ]
      ]
    },
    {
      "Translate": {
        "X": -3.75,
        "Y": 15.0,
        "Z": -11.25
      },
      "Actor name": "LampJungle",
      "Actor params": [
        0,
        false
      ],
      "Conditions": [
        [
          null,
          4
        ],
        [
          1,
          2
        ]
      ]
    },
    {
      "Translate": {
        "X": 2.25,
        "Y": 15.0,
        "Z": -11.25
      },
      "Actor name": "LampJungle",
      "Actor params": [
        0,
        false
      ],
      "Conditions": [
        [
          null,
          4
        ],
        [
          1,
          2
        ]
      ]
    },
    {
      "Translate": {
        "X": -6.75,
        "Y": 15.0,
        "Z": -3.75
      },
      "Actor name": "BoxWooden",
      "Actor params": [],
      "Conditions": []
    },
    {
      "Translate": {
        "X": 5.25,
        "Y": 15.0,
        "Z": -14.25
      },
      "Actor name": "BoxWooden",
      "Actor params": [],
      "Conditions": []
    },
    {
      "Translate": {
        "X": 6.75,
        "Y": 15.0,
        "Z": -5.25
      },
      "Actor name": "DoorClose",
      "Actor params": [
        1,
        2,
        "",
        0,
        0,
        1
      ],
      "Conditions": [
        [
          0,
          3
        ]
      ]
    },
    {
      "Translate": {
        "X": -0.75,
        "Y": 15.0,
        "Z": -14.25
      },
      "Actor name": "SparkBox",
      "Actor params": [
        2
      ],
      "Conditions": [
        [
          0,
          3
        ]
      ]
    },
    {
      "Translate": {
        "X": 17.25,
        "Y": 15.0,
        "Z": -9.75
      },
      "Actor name": "TagTailorPlayer",
      "Actor params": [
        "S_Dungeon104_003_Effect_00"
      ],
      "Conditions": []
    },
    {
      "Translate": {
        "X": 17.25,
        "Y": 17.25,
        "Z": -14.25
      },
      "Actor name": "TagRoomLocker",
      "Actor params": [
        "",
        "",
        ""
      ],
      "Conditions": [
        [
          0,
          3
        ]
      ]
    },
    {
      "Translate": {
        "X": 17.25,
        "Y": 15.0,
        "Z": -9.75
      },
      "Actor name": "MapStatic",
      "Actor params": [
        "S_Dungeon104_003",
        "",
        "",
        0,
        1
      ],
      "Conditions": []
    },
    {
      "Translate": {
        "X": 23.25,
        "Y": 13.5,
        "Z": -6.75
      },
      "Actor name": "Spark00",
      "Actor params": [
        2,
        1
      ],
      "Conditions": []
    },
    {
      "Translate": {
        "X": 12.75,
        "Y": 13.5,
        "Z": -11.25
      },
      "Actor name": "Spark00",
      "Actor params": [
        2,
        0
      ],
      "Conditions": []
    },
    {
      "Translate": {
        "X": 15.75,
        "Y": 13.5,
        "Z": -6.75
      },
      "Actor name": "GhomaBaby",
      "Actor params": [],
      "Conditions": []
    },
    {
      "Translate": {
        "X": 24.75,
        "Y": 15.0,
        "Z": -8.25
      },
      "Actor name": "GhomaEgg",
      "Actor params": [],
      "Conditions": []
    },
    {
      "Translate": {
        "X": 21.75,
        "Y": 15.0,
        "Z": -12.75
      },
      "Actor name": "GhomaEgg",
      "Actor params": [],
      "Conditions": []
    },
    {
      "Translate": {
        "X": 23.25,
        "Y": 15.0,
        "Z": -5.25
      },
      "Actor name": "GhomaEgg",
      "Actor params": [],
      "Conditions": []
    },
    {
      "Translate": {
        "X": 11.25,
        "Y": 15.0,
        "Z": -12.75
      },
      "Actor name": "GhomaEgg",
      "Actor params": [],
      "Conditions": []
    },
    {
      "Translate": {
        "X": 17.25,
        "Y": 15.0,
        "Z": -9.75
      },
      "Actor name": "LampJungle",
      "Actor params": [
        0,
        false
      ],
      "Conditions": [
        [
          null,
          4
        ],
        [
          1,
          2
        ]
      ]
    },
    {
      "Translate": {
        "X": 15.75,
        "Y": 15.0,
        "Z": -5.25
      },
      "Actor name": "SpiderWeb",
      "Actor params": [
        "Large__MI_SpiderWeb_00",
        false
      ],
      "Conditions": []
    },
    {
      "Translate": {
        "X": 12.75,
        "Y": 15.0,
        "Z": -11.25
      },
      "Actor name": "SpiderWeb",
      "Actor params": [
        "Large__MI_SpiderWeb_00",
        false
      ],
      "Conditions": []
    },
    {
      "Translate": {
        "X": 21.75,
        "Y": 15.0,
        "Z": -12.75
      },
      "Actor name": "SpiderWeb",
      "Actor params": [
        "Large__MI_SpiderWeb_00",
        false
      ],
      "Conditions": []
    },
    {
      "Translate": {
        "X": 23.25,
        "Y": 15.0,
        "Z": -6.75
      },
      "Actor name": "SpiderWeb",
      "Actor params": [
        "Large__MI_SpiderWeb_00",
        false
      ],
      "Conditions": []
    },
    {
      "Translate": {
        "X": 18.75,
        "Y": 13.5,
        "Z": -6.75
      },
      "Actor name": "BoxWooden",
      "Actor params": [],
      "Conditions": []
    },
    {
      "Translate": {
        "X": 12.75,
        "Y": 13.5,
        "Z": -6.75
      },
      "Actor name": "BoxWooden",
      "Actor params": [],
      "Conditions": []
    },
    {
      "Translate": {
        "X": 20.25,
        "Y": 13.5,
        "Z": -6.75
      },
      "Actor name": "RockCave",
      "Actor params": [],
      "Conditions": []
    },
    {
      "Translate": {
        "X": 21.75,
        "Y": 13.5,
        "Z": -9.75
      },
      "Actor name": "RockCave",
      "Actor params": [],
      "Conditions": []
    },
    {
      "Translate": {
        "X": 12.75,
        "Y": 13.5,
        "Z": -8.25
      },
      "Actor name": "RockCave",
      "Actor params": [],
      "Conditions": []
    },
    {
      "Translate": {
        "X": 23.25,
        "Y": 13.5,
        "Z": -14.25
      },
      "Actor name": "SparkBox",
      "Actor params": [
        2
      ],
      "Conditions": [
        [
          0,
          3
        ]
      ]
    },
    {
      "Translate": {
        "X": 17.25,
        "Y": 15.0,
        "Z": -15.75
      },
      "Actor name": "DoorClose",
      "Actor params": [
        1,
        2,
        "",
        0,
        0,
        1
      ],
      "Conditions": [
        [
          0,
          3
        ]
      ]
    },
    {
      "Translate": {
        "X": 17.25,
        "Y": 13.5,
        "Z": -3.75
      },
      "Actor name": "ItemRupeeRed",
      "Actor params": [],
      "Conditions": []
    },
    {
      "Translate": {
        "X": 23.25,
        "Y": 15.0,
        "Z": -24.75
      },
      "Actor name": "TagTailorPlayer",
      "Actor params": [
        "S_Dungeon104_004_Effect_00"
      ],
      "Conditions": []
    },
    {
      "Translate": {
        "X": 17.25,
        "Y": 17.25,
        "Z": -30.75
      },
      "Actor name": "TagRoomLocker",
      "Actor params": [
        "",
        "",
        ""
      ],
      "Conditions": [
        [
          0,
          3
        ]
      ]
    },
    {
      "Translate": {
        "X": 23.25,
        "Y": 15.0,
        "Z": -24.75
      },
      "Actor name": "MapStatic",
      "Actor params": [
        "S_Dungeon104_004",
        "",
        "",
        0,
        1
      ],
      "Conditions": []
    },
    {
      "Translate": {
        "X": 29.25,
        "Y": 15.0,
        "Z": -27.75
      },
      "Actor name": "Spark00",
      "Actor params": [
        3,
        0
      ],
      "Conditions": []
    },
    {
      "Translate": {
        "X": 23.25,
        "Y": 15.0,
        "Z": -20.25
      },
      "Actor name": "Spark00",
      "Actor params": [
        3,
        0
      ],
      "Conditions": []
    },
    {
      "Translate": {
        "X": 21.75,
        "Y": 15.0,
        "Z": -18.75
      },
      "Actor name": "Spark00",
      "Actor params": [
        0,
        0
      ],
      "Conditions": []
    },
    {
      "Translate": {
        "X": 27.75,
        "Y": 15.0,
        "Z": -29.25
      },
      "Actor name": "Armos",
      "Actor params": [],
      "Conditions": []
    },
    {
      "Translate": {
        "X": 17.25,
        "Y": 15.0,
        "Z": -32.25
      },
      "Actor name": "DoorClose",
      "Actor params": [
        1,
        2,
        "",
        0,
        0,
        1
      ],
      "Conditions": [
        [
          0,
          3
        ]
      ]
    },
    {
      "Translate": {
        "X": 24.75,
        "Y": 15.0,
        "Z": -24.75
      },
      "Actor name": "SparkBox",
      "Actor params": [
        3
      ],
      "Conditions": [
        [
          0,
          3
        ]
      ]
    },
    {
      "Translate": {
        "X": 24.75,
        "Y": 15.0,
        "Z": -20.25
      },
      "Actor name": "RockCave",
      "Actor params": [],
      "Conditions": []
    },
    {
      "Translate": {
        "X": 17.25,
        "Y": 15.75,
        "Z": -32.25
      },
      "Actor name": "SensorFloorChange",
      "Actor params": [
        "S110_R006_Start",
        "FloorChangeCommon:TopLadderDown",
        null,
        null,
        null,
        null,
        "None",
        ""
      ],
      "Conditions": []
    },
    {
      "Translate": {
        "X": 108.0,
        "Y": -30.0,
        "Z": -0.75
      },
      "Actor name": "TagTailorPlayer",
      "Actor params": [
        "S_Dungeon104_006_Effect_00"
      ],
      "Conditions": []
    },
    {
      "Translate": {
        "X": 120.75,
        "Y": -16.875,
        "Z": 0.0
      },
      "Actor name": "TagTailorPlayer",
      "Actor params": [
        "TagTailorPlayer_Lamp_Wall_Side_00_SD104"
      ],
      "Conditions": []
    },
    {
      "Translate": {
        "X": 126.0,
        "Y": -25.125,
        "Z": 0.0
      },
      "Actor name": "TagTailorPlayer",
      "Actor params": [
        "TagTailorPlayer_Lamp_Wall_Side_00_SD104"
      ],
      "Conditions": []
    },
    {
      "Translate": {
        "X": 108.0,
        "Y": -30.0,
        "Z": -0.75
      },
      "Actor name": "MapStatic",
      "Actor params": [
        "S_Dungeon104_006",
        "",
        "",
        0,
        1
      ],
      "Conditions": []
    },
    {
      "Translate": {
        "X": 126.0,
        "Y": -28.5,
        "Z": -0.75
      },
      "Actor name": "MapAbyss",
      "Actor params": [],
      "Conditions": []
    },
    {
      "Translate": {
        "X": 113.25,
        "Y": -27.0,
        "Z": -0.75
      },
      "Actor name": "MapLadder",
      "Actor params": [],
      "Conditions": []
    },
    {
      "Translate": {
        "X": 110.25,
        "Y": -19.5,
        "Z": -0.75
      },
      "Actor name": "MapLadder",
      "Actor params": [],
      "Conditions": []
    },
    {
      "Translate": {
        "X": 110.25,
        "Y": -12.75,
        "Z": -0.75
      },
      "Actor name": "SensorFloorChange",
      "Actor params": [
        "S110_R004_Start",
        "FloorChangeCommon:LadderUp",
        1,
        null,
        null,
        null,
        "None",
        ""
      ],
      "Conditions": []
    },
    {
      "Translate": {
        "X": 138.75,
        "Y": -18.75,
        "Z": -0.75
      },
      "Actor name": "SensorCameraScrollContorol",
      "Actor params": [
        0,
        1,
        0,
        0.0,
        1.5,
        0.0
      ],
      "Conditions": []
    },
    {
      "Translate": {
        "X": 121.5,
        "Y": -21.0,
        "Z": -0.75
      },
      "Actor name": "Spark00",
      "Actor params": [
        1,
        1
      ],
      "Conditions": []
    },
    {
      "Translate": {
        "X": 130.5,
        "Y": -18.0,
        "Z": -0.75
      },
      "Actor name": "Spark00",
      "Actor params": [
        0,
        0
      ],
      "Conditions": []
    },
    {
      "Translate": {
        "X": 141.0,
        "Y": -18.0,
        "Z": -0.75
      },
      "Actor name": "Spark00",
      "Actor params": [
        1,
        1
      ],
      "Conditions": []
    },
    {
      "Translate": {
        "X": 130.5,
        "Y": -18.0,
        "Z": -2.25
      },
      "Actor name": "TreasureBox",
      "Actor params": [
        "true",
        15,
        0,
        0,
        "",
        "",
        1,
        false
      ],
      "Conditions": []
    },
    {
      "Translate": {
        "X": 148.5,
        "Y": -33.0,
        "Z": -0.75
      },
      "Actor name": "TagTailorPlayer",
      "Actor params": [
        "S_Dungeon104_007_Effect_00"
      ],
      "Conditions": []
    },
    {
      "Translate": {
        "X": 173.25,
        "Y": -15.75,
        "Z": -0.75
      },
      "Actor name": "TagRoomLocker",
      "Actor params": [
        "",
        "",
        ""
      ],
      "Conditions": [
        [
          0,
          3
        ]
      ]
    },
    {
      "Translate": {
        "X": 159.0,
        "Y": -15.375,
        "Z": 0.0
      },
      "Actor name": "TagTailorPlayer",
      "Actor params": [
        "TagTailorPlayer_Lamp_Wall_Side_00_SD104"
      ],
      "Conditions": []
    },
    {
      "Translate": {
        "X": 148.5,
        "Y": -33.0,
        "Z": -0.75
      },
      "Actor name": "MapStatic",
      "Actor params": [
        "S_Dungeon104_007",
        "",
        "",
        0,
        1
      ],
      "Conditions": []
    },
    {
      "Translate": {
        "X": 164.25,
        "Y": -31.5,
        "Z": -0.75
      },
      "Actor name": "MapPond",
      "Actor params": [],
      "Conditions": []
    },
    {
      "Translate": {
        "X": 163.5,
        "Y": -18.0,
        "Z": -0.75
      },
      "Actor name": "MapBoulderingWall",
      "Actor params": [],
      "Conditions": []
    },
    {
      "Translate": {
        "X": 163.5,
        "Y": -15.0,
        "Z": -0.75
      },
      "Actor name": "MapBoulderingWall",
      "Actor params": [],
      "Conditions": []
    },
    {
      "Translate": {
        "X": 157.5,
        "Y": -18.0,
        "Z": -0.75
      },
      "Actor name": "Spark00",
      "Actor params": [
        0,
        0
      ],
      "Conditions": []
    },
    {
      "Translate": {
        "X": 171.75,
        "Y": -22.5,
        "Z": -0.75
      },
      "Actor name": "Spark00",
      "Actor params": [
        0,
        0
      ],
      "Conditions": []
    },
    {
      "Translate": {
        "X": 156.75,
        "Y": -28.5,
        "Z": -0.75
      },
      "Actor name": "Spark00",
      "Actor params": [
        0,
        0
      ],
      "Conditions": []
    },
    {
      "Translate": {
        "X": 159.75,
        "Y": -29.25,
        "Z": -0.75
      },
      "Actor name": "Biri",
      "Actor params": [],
      "Conditions": []
    },
    {
      "Translate": {
        "X": 161.25,
        "Y": -30.75,
        "Z": -0.75
      },
      "Actor name": "Biri",
      "Actor params": [],
      "Conditions": []
    },
    {
      "Translate": {
        "X": 163.5,
        "Y": -17.25,
        "Z": -1.5
      },
      "Actor name": "SparkBox",
      "Actor params": [
        3
      ],
      "Conditions": [
        [
          0,
          3
        ]
      ]
    },
    {
      "Translate": {
        "X": 174.75,
        "Y": -18.0,
        "Z": -0.75
      },
      "Actor name": "DoorClose",
      "Actor params": [
        1,
        2,
        "",
        0,
        0,
        1
      ],
      "Conditions": [
        [
          0,
          3
        ]
      ]
    },
    {
      "Translate": {
        "X": 156.75,
        "Y": -19.5,
        "Z": -0.75
      },
      "Actor name": "BoxWooden",
      "Actor params": [],
      "Conditions": []
    },
    {
      "Translate": {
        "X": 158.25,
        "Y": -19.5,
        "Z": -0.75
      },
      "Actor name": "BoxWooden",
      "Actor params": [],
      "Conditions": []
    },
    {
      "Translate": {
        "X": 173.25,
        "Y": -25.5,
        "Z": -0.75
      },
      "Actor name": "RockCave",
      "Actor params": [],
      "Conditions": []
    },
    {
      "Translate": {
        "X": 173.25,
        "Y": -24.0,
        "Z": -0.75
      },
      "Actor name": "RockCave",
      "Actor params": [],
      "Conditions": []
    },
    {
      "Translate": {
        "X": 175.5,
        "Y": -21.0,
        "Z": -0.75
      },
      "Actor name": "TagTailorPlayer",
      "Actor params": [
        "S_Dungeon104_009_Effect_00"
      ],
      "Conditions": []
    },
    {
      "Translate": {
        "X": 175.5,
        "Y": -21.0,
        "Z": -0.75
      },
      "Actor name": "MapStatic",
      "Actor params": [
        "S_Dungeon104_009",
        "",
        "",
        0,
        1
      ],
      "Conditions": []
    },
    {
      "Translate": {
        "X": 187.5,
        "Y": -15.0,
        "Z": -0.75
      },
      "Actor name": "MapBoulderingWall",
      "Actor params": [],
      "Conditions": []
    },
    {
      "Translate": {
        "X": 189.75,
        "Y": -13.5,
        "Z": -0.75
      },
      "Actor name": "MapBoulderingWall",
      "Actor params": [],
      "Conditions": []
    },
    {
      "Translate": {
        "X": 179.25,
        "Y": -18.0,
        "Z": -0.75
      },
      "Actor name": "MapBoulderingWall",
      "Actor params": [],
      "Conditions": []
    },
    {
      "Translate": {
        "X": 182.25,
        "Y": -16.5,
        "Z": -0.75
      },
      "Actor name": "MapBoulderingWall",
      "Actor params": [],
      "Conditions": []
    },
    {
      "Translate": {
        "X": 179.25,
        "Y": -12.0,
        "Z": -0.75
      },
      "Actor name": "MapBoulderingWall",
      "Actor params": [],
      "Conditions": []
    },
    {
      "Translate": {
        "X": 177.75,
        "Y": -15.0,
        "Z": -0.75
      },
      "Actor name": "MapBoulderingWall",
      "Actor params": [],
      "Conditions": []
    },
    {
      "Translate": {
        "X": 186.75,
        "Y": -16.5,
        "Z": -0.75
      },
      "Actor name": "MapBoulderingWall",
      "Actor params": [],
      "Conditions": []
    },
    {
      "Translate": {
        "X": 180.75,
        "Y": -18.0,
        "Z": -0.75
      },
      "Actor name": "MapBoulderingWall",
      "Actor params": [],
      "Conditions": []
    },
    {
      "Translate": {
        "X": 180.75,
        "Y": -13.5,
        "Z": -0.75
      },
      "Actor name": "MapBoulderingWall",
      "Actor params": [],
      "Conditions": []
    },
    {
      "Translate": {
        "X": 185.25,
        "Y": -13.5,
        "Z": -0.75
      },
      "Actor name": "MapBoulderingWall",
      "Actor params": [],
      "Conditions": []
    },
    {
      "Translate": {
        "X": 188.25,
        "Y": -12.0,
        "Z": -0.75
      },
      "Actor name": "MapBoulderingWall",
      "Actor params": [],
      "Conditions": []
    },
    {
      "Translate": {
        "X": 188.25,
        "Y": -18.0,
        "Z": -0.75
      },
      "Actor name": "Pot",
      "Actor params": [],
      "Conditions": []
    },
    {
      "Translate": {
        "X": 186.75,
        "Y": -18.0,
        "Z": -0.75
      },
      "Actor name": "Pot",
      "Actor params": [],
      "Conditions": []
    },
    {
      "Translate": {
        "X": 183.75,
        "Y": -13.5,
        "Z": -0.75
      },
      "Actor name": "Pot",
      "Actor params": [],
      "Conditions": []
    },
    {
      "Translate": {
        "X": 182.25,
        "Y": -13.5,
        "Z": -0.75
      },
      "Actor name": "Pot",
      "Actor params": [],
      "Conditions": []
    },
    {
      "Translate": {
        "X": 201.75,
        "Y": -19.5,
        "Z": -0.75
      },
      "Actor name": "MapBoulderingWall",
      "Actor params": [],
      "Conditions": []
    },
    {
      "Translate": {
        "X": 206.25,
        "Y": -19.5,
        "Z": -0.75
      },
      "Actor name": "MapBoulderingWall",
      "Actor params": [],
      "Conditions": []
    },
    {
      "Translate": {
        "X": 218.25,
        "Y": -19.5,
        "Z": -0.75
      },
      "Actor name": "MapBoulderingWall",
      "Actor params": [],
      "Conditions": []
    },
    {
      "Translate": {
        "X": 213.75,
        "Y": -19.5,
        "Z": -0.75
      },
      "Actor name": "MapBoulderingWall",
      "Actor params": [],
      "Conditions": []
    },
    {
      "Translate": {
        "X": 212.25,
        "Y": -10.5,
        "Z": -0.75
      },
      "Actor name": "MapBoulderingWall",
      "Actor params": [],
      "Conditions": []
    },
    {
      "Translate": {
        "X": 200.25,
        "Y": -19.5,
        "Z": -0.75
      },
      "Actor name": "MapBoulderingWall",
      "Actor params": [],
      "Conditions": []
    },
    {
      "Translate": {
        "X": 210.0,
        "Y": -12.0,
        "Z": -0.75
      },
      "Actor name": "MapBoulderingWall",
      "Actor params": [],
      "Conditions": []
    },
    {
      "Translate": {
        "X": 210.0,
        "Y": -7.5,
        "Z": -0.75
      },
      "Actor name": "MapBoulderingWall",
      "Actor params": [],
      "Conditions": []
    },
    {
      "Translate": {
        "X": 219.75,
        "Y": -18.0,
        "Z": -0.75
      },
      "Actor name": "MapBoulderingWall",
      "Actor params": [],
      "Conditions": []
    },
    {
      "Translate": {
        "X": 207.75,
        "Y": -10.5,
        "Z": -0.75
      },
      "Actor name": "MapBoulderingWall",
      "Actor params": [],
      "Conditions": []
    },
    {
      "Translate": {
        "X": 224.25,
        "Y": -18.0,
        "Z": -0.75
      },
      "Actor name": "MapBoulderingWall",
      "Actor params": [],
      "Conditions": []
    },
    {
      "Translate": {
        "X": 210.75,
        "Y": -18.0,
        "Z": -0.75
      },
      "Actor name": "MapStatic",
      "Actor params": [
        "S_Dungeon104_010",
        "",
        "",
        0,
        1
      ],
      "Conditions": []
    },
    {
      "Translate": {
        "X": 210.75,
        "Y": -18.0,
        "Z": -0.75
      },
      "Actor name": "TagTailorPlayer",
      "Actor params": [
        "S_Dungeon104_010_Effect_00"
      ],
      "Conditions": []
    },
    {
      "Translate": {
        "X": 198.0,
        "Y": -11.625,
        "Z": 0.0
      },
      "Actor name": "TagTailorPlayer",
      "Actor params": [
        "TagTailorPlayer_Lamp_Wall_Side_00_SD104"
      ],
      "Conditions": []
    },
    {
      "Translate": {
        "X": 214.5,
        "Y": -8.625,
        "Z": 0.0
      },
      "Actor name": "TagTailorPlayer",
      "Actor params": [
        "TagTailorPlayer_Lamp_Wall_Side_00_SD104"
      ],
      "Conditions": []
    },
    {
      "Translate": {
        "X": 210.0,
        "Y": -13.5,
        "Z": -0.75
      },
      "Actor name": "Balom01",
      "Actor params": [
        1,
        0
      ],
      "Conditions": [
        [
          "EvF_BalomLv2Dead",
          1
        ]
      ]
    },
    {
      "Translate": {
        "X": 207.0,
        "Y": -18.75,
        "Z": -0.75
      },
      "Actor name": "BalomPiece01",
      "Actor params": [
        "BalomPiece0"
      ],
      "Conditions": []
    },
    {
      "Translate": {
        "X": 210.0,
        "Y": -18.75,
        "Z": -0.75
      },
      "Actor name": "BalomPiece01",
      "Actor params": [
        "BalomPiece1"
      ],
      "Conditions": []
    },
    {
      "Translate": {
        "X": 213.0,
        "Y": -18.75,
        "Z": -0.75
      },
      "Actor name": "BalomPiece01",
      "Actor params": [
        "BalomPiece2"
      ],
      "Conditions": []
    },
    {
      "Translate": {
        "X": 216.0,
        "Y": -18.75,
        "Z": -0.75
      },
      "Actor name": "BalomPiece01",
      "Actor params": [
        "BalomPiece3"
      ],
      "Conditions": []
    },
    {
      "Translate": {
        "X": 219.0,
        "Y": -18.75,
        "Z": -0.75
      },
      "Actor name": "BalomPiece01",
      "Actor params": [
        "BalomPiece4"
      ],
      "Conditions": []
    },
    {
      "Translate": {
        "X": 195.75,
        "Y": -13.5,
        "Z": -0.75
      },
      "Actor name": "DoorClose",
      "Actor params": [
        1,
        1,
        "",
        0,
        0,
        1
      ],
      "Conditions": []
    },
    {
      "Translate": {
        "X": 210.0,
        "Y": -9.0,
        "Z": -0.75
      },
      "Actor name": "WarpBoss",
      "Actor params": [
        "S104_R001_WarpBoss",
        "Switch0"
      ],
      "Conditions": [
        [
          "EvF_BalomLv2Dead",
          1
        ]
      ]
    },
    {
      "Translate": {
        "X": 225.75,
        "Y": -18.0,
        "Z": -0.75
      },
      "Actor name": "Pot",
      "Actor params": [
        29
      ],
      "Conditions": []
    },
    {
      "Translate": {
        "X": 198.75,
        "Y": -18.0,
        "Z": -0.75
      },
      "Actor name": "Pot",
      "Actor params": [
        29
      ],
      "Conditions": []
    },
    {
      "Translate": {
        "X": 197.25,
        "Y": -18.0,
        "Z": -0.75
      },
      "Actor name": "Pot",
      "Actor params": [
        29
      ],
      "Conditions": []
    },
    {
      "Translate": {
        "X": 227.25,
        "Y": -18.0,
        "Z": -0.75
      },
      "Actor name": "Pot",
      "Actor params": [
        29
      ],
      "Conditions": []
    },
    {
      "Translate": {
        "X": 210.0,
        "Y": -13.5,
        "Z": -0.75
      },
      "Actor name": "ItemHeartPiece",
      "Actor params": [
        16
      ],
      "Conditions": [
        [
          null,
          4
        ],
        [
          "EvF_BalomLv2Dead",
          1
        ]
      ]
    },
    {
      "Translate": {
        "X": 212.625,
        "Y": -13.5,
        "Z": -0.75
      },
      "Actor name": "ItemRupeeBlue",
      "Actor params": [],
      "Conditions": [
        [
          0,
          3
        ],
        [
          "EvF_BalomLv2Dead",
          1
        ],
        [
          0,
          3
        ]
      ]
    },
    {
      "Translate": {
        "X": 211.875,
        "Y": -13.5,
        "Z": -0.75
      },
      "Actor name": "ItemRupeeRed",
      "Actor params": [],
      "Conditions": [
        [
          1,
          3
        ],
        [
          "EvF_BalomLv2Dead",
          1
        ],
        [
          1,
          3
        ]
      ]
    },
    {
      "Translate": {
        "X": 211.125,
        "Y": -13.5,
        "Z": -0.75
      },
      "Actor name": "ItemMachineCoupon",
      "Actor params": [],
      "Conditions": [
        [
          3,
          3
        ],
        [
          "EvF_BalomLv2Dead",
          1
        ],
        [
          3,
          3
        ]
      ]
    },
    {
      "Translate": {
        "X": 207.375,
        "Y": -13.5,
        "Z": -0.75
      },
      "Actor name": "ItemRupeePurple",
      "Actor params": [],
      "Conditions": [
        [
          2,
          3
        ],
        [
          "EvF_BalomLv2Dead",
          1
        ],
        [
          2,
          3
        ]
      ]
    },
    {
      "Translate": {
        "X": 208.875,
        "Y": -13.5,
        "Z": -0.75
      },
      "Actor name": "ItemMachineCoupon",
      "Actor params": [],
      "Conditions": [
        [
          4,
          3
        ],
        [
          "EvF_BalomLv2Dead",
          1
        ],
        [
          4,
          3
        ]
      ]
    },
    {
      "Translate": {
        "X": 195.75,
        "Y": -12.75,
        "Z": -0.75
      },
      "Actor name": "SensorBossAppearBox",
      "Actor params": [],
      "Conditions": []
    },
    {
      "Translate": {
        "X": -0.75,
        "Y": 15.0,
        "Z": 12.75
      },
      "Actor name": "TagLightActor",
      "Actor params": [
        0,
        0,
        false,
        1.0
      ],
      "Conditions": []
    },
    {
      "Translate": {
        "X": 5.25,
        "Y": 15.0,
        "Z": -5.25
      },
      "Actor name": "TagLightActor",
      "Actor params": [
        1,
        1,
        false,
        1.0
      ],
      "Conditions": []
    },
    {
      "Translate": {
        "X": -0.75,
        "Y": 15.0,
        "Z": -14.25
      },
      "Actor name": "TagLightActor",
      "Actor params": [
        2,
        2,
        false,
        1.0
      ],
      "Conditions": []
    },
    {
      "Translate": {
        "X": -0.75,
        "Y": 15.0,
        "Z": -2.25
      },
      "Actor name": "TagLightActor",
      "Actor params": [
        3,
        3,
        false,
        1.0
      ],
      "Conditions": []
    },
    {
      "Translate": {
        "X": 17.25,
        "Y": 15.0,
        "Z": -9.75
      },
      "Actor name": "TagLightActor",
      "Actor params": [
        4,
        4,
        false,
        1.0
      ],
      "Conditions": []
    },
    {
      "Translate": {
        "X": 9.75,
        "Y": 15.0,
        "Z": -5.25
      },
      "Actor name": "TagLightActor",
      "Actor params": [
        1,
        5,
        false,
        1.0
      ],
      "Conditions": []
    },
    {
      "Translate": {
        "X": 17.25,
        "Y": 15.0,
        "Z": -14.25
      },
      "Actor name": "TagLightActor",
      "Actor params": [
        5,
        6,
        false,
        1.0
      ],
      "Conditions": []
    },
    {
      "Translate": {
        "X": 17.25,
        "Y": 15.0,
        "Z": -17.25
      },
      "Actor name": "TagLightActor",
      "Actor params": [
        6,
        3,
        false,
        1.0
      ],
      "Conditions": []
    },
    {
      "Translate": {
        "X": 17.25,
        "Y": 15.0,
        "Z": -30.75
      },
      "Actor name": "TagLightActor",
      "Actor params": [
        5,
        6,
        false,
        1.0
      ],
      "Conditions": []
    },
    {
      "Translate": {
        "X": 24.0,
        "Y": 15.0,
        "Z": -24.75
      },
      "Actor name": "TagLightActor",
      "Actor params": [
        7,
        7,
        false,
        1.0
      ],
      "Conditions": []
    },
    {
      "Translate": {
        "X": 110.25,
        "Y": -12.75,
        "Z": -0.75
      },
      "Actor name": "TagLightActor",
      "Actor params": [
        8,
        8,
        false,
        1.0
      ],
      "Conditions": []
    },
    {
      "Translate": {
        "X": 111.75,
        "Y": -19.5,
        "Z": -0.75
      },
      "Actor name": "TagLightActor",
      "Actor params": [
        9,
        9,
        false,
        1.0
      ],
      "Conditions": []
    },
    {
      "Translate": {
        "X": 117.0,
        "Y": -27.0,
        "Z": -0.75
      },
      "Actor name": "TagLightActor",
      "Actor params": [
        10,
        10,
        false,
        1.0
      ],
      "Conditions": []
    },
    {
      "Translate": {
        "X": 121.5,
        "Y": -21.0,
        "Z": -0.75
      },
      "Actor name": "TagLightActor",
      "Actor params": [
        11,
        11,
        false,
        1.0
      ],
      "Conditions": []
    },
    {
      "Translate": {
        "X": 127.5,
        "Y": -18.0,
        "Z": -0.75
      },
      "Actor name": "TagLightActor",
      "Actor params": [
        12,
        12,
        false,
        1.0
      ],
      "Conditions": []
    },
    {
      "Translate": {
        "X": 133.5,
        "Y": -24.0,
        "Z": -0.75
      },
      "Actor name": "TagLightActor",
      "Actor params": [
        13,
        13,
        false,
        1.0
      ],
      "Conditions": []
    },
    {
      "Translate": {
        "X": 141.0,
        "Y": -24.0,
        "Z": -0.75
      },
      "Actor name": "TagLightActor",
      "Actor params": [
        14,
        14,
        false,
        1.0
      ],
      "Conditions": []
    },
    {
      "Translate": {
        "X": 138.0,
        "Y": -15.0,
        "Z": -0.75
      },
      "Actor name": "TagLightActor",
      "Actor params": [
        15,
        15,
        false,
        1.0
      ],
      "Conditions": []
    },
    {
      "Translate": {
        "X": 143.25,
        "Y": -18.0,
        "Z": -0.75
      },
      "Actor name": "TagLightActor",
      "Actor params": [
        16,
        16,
        false,
        1.0
      ],
      "Conditions": []
    },
    {
      "Translate": {
        "X": 133.5,
        "Y": -18.0,
        "Z": -0.75
      },
      "Actor name": "TagLightActor",
      "Actor params": [
        17,
        17,
        false,
        1.0
      ],
      "Conditions": []
    },
    {
      "Translate": {
        "X": 147.75,
        "Y": -18.0,
        "Z": -0.75
      },
      "Actor name": "TagLightActor",
      "Actor params": [
        18,
        18,
        false,
        1.0
      ],
      "Conditions": []
    },
    {
      "Translate": {
        "X": 149.25,
        "Y": -18.0,
        "Z": -0.75
      },
      "Actor name": "TagLightActor",
      "Actor params": [
        19,
        19,
        false,
        1.0
      ],
      "Conditions": []
    },
    {
      "Translate": {
        "X": 154.125,
        "Y": -18.0,
        "Z": -0.75
      },
      "Actor name": "TagLightActor",
      "Actor params": [
        20,
        20,
        false,
        1.0
      ],
      "Conditions": []
    },
    {
      "Translate": {
        "X": 163.5,
        "Y": -18.0,
        "Z": -0.75
      },
      "Actor name": "TagLightActor",
      "Actor params": [
        21,
        21,
        false,
        1.0
      ],
      "Conditions": []
    },
    {
      "Translate": {
        "X": 169.5,
        "Y": -18.0,
        "Z": -0.75
      },
      "Actor name": "TagLightActor",
      "Actor params": [
        22,
        22,
        false,
        1.0
      ],
      "Conditions": []
    },
    {
      "Translate": {
        "X": 159.0,
        "Y": -25.5,
        "Z": -0.75
      },
      "Actor name": "TagLightActor",
      "Actor params": [
        23,
        23,
        false,
        1.0
      ],
      "Conditions": []
    },
    {
      "Translate": {
        "X": 159.75,
        "Y": -31.5,
        "Z": -0.75
      },
      "Actor name": "TagLightActor",
      "Actor params": [
        24,
        24,
        false,
        1.0
      ],
      "Conditions": []
    },
    {
      "Translate": {
        "X": 169.5,
        "Y": -25.5,
        "Z": -0.75
      },
      "Actor name": "TagLightActor",
      "Actor params": [
        25,
        25,
        false,
        1.0
      ],
      "Conditions": []
    },
    {
      "Translate": {
        "X": 174.75,
        "Y": -18.0,
        "Z": -0.75
      },
      "Actor name": "TagLightActor",
      "Actor params": [
        19,
        18,
        false,
        1.0
      ],
      "Conditions": []
    },
    {
      "Translate": {
        "X": 176.25,
        "Y": -18.0,
        "Z": -0.75
      },
      "Actor name": "TagLightActor",
      "Actor params": [
        26,
        19,
        false,
        1.0
      ],
      "Conditions": []
    },
    {
      "Translate": {
        "X": 192.75,
        "Y": -13.5,
        "Z": -0.75
      },
      "Actor name": "TagLightActor",
      "Actor params": [
        26,
        18,
        false,
        1.0
      ],
      "Conditions": []
    },
    {
      "Translate": {
        "X": 183.0,
        "Y": -18.0,
        "Z": -0.75
      },
      "Actor name": "TagLightActor",
      "Actor params": [
        27,
        26,
        false,
        1.0
      ],
      "Conditions": []
    },
    {
      "Translate": {
        "X": 183.0,
        "Y": -13.5,
        "Z": -0.75
      },
      "Actor name": "TagLightActor",
      "Actor params": [
        28,
        27,
        false,
        1.0
      ],
      "Conditions": []
    },
    {
      "Translate": {
        "X": 194.25,
        "Y": -13.5,
        "Z": -0.75
      },
      "Actor name": "TagLightActor",
      "Actor params": [
        29,
        19,
        false,
        1.0
      ],
      "Conditions": []
    },
    {
      "Translate": {
        "X": 201.0,
        "Y": -13.5,
        "Z": -0.75
      },
      "Actor name": "TagLightActor",
      "Actor params": [
        30,
        28,
        false,
        1.0
      ],
      "Conditions": []
    },
    {
      "Translate": {
        "X": 210.0,
        "Y": -13.5,
        "Z": -0.75
      },
      "Actor name": "TagLightActor",
      "Actor params": [
        31,
        29,
        false,
        1.0
      ],
      "Conditions": []
    },
    {
      "Translate": {
        "X": 219.0,
        "Y": -13.5,
        "Z": -0.75
      },
      "Actor name": "TagLightActor",
      "Actor params": [
        32,
        28,
        false,
        1.0
      ],
      "Conditions": []
    },
    {
      "Translate": {
        "X": 210.0,
        "Y": -19.5,
        "Z": -0.75
      },
      "Actor name": "TagLightActor",
      "Actor params": [
        33,
        30,
        false,
        1.0
      ],
      "Conditions": []
    },
    {
      "Translate": {
        "X": 201.0,
        "Y": -19.5,
        "Z": -0.75
      },
      "Actor name": "TagLightActor",
      "Actor params": [
        34,
        31,
        false,
        1.0
      ],
      "Conditions": []
    },
    {
      "Translate": {
        "X": 219.0,
        "Y": -19.5,
        "Z": -0.75
      },
      "Actor name": "TagLightActor",
      "Actor params": [
        35,
        32,
        false,
        1.0
      ],
      "Conditions": []
    },
    {
      "Translate": {
        "X": 219.0,
        "Y": -7.5,
        "Z": -0.75
      },
      "Actor name": "TagLightActor",
      "Actor params": [
        36,
        33,
        false,
        1.0
      ],
      "Conditions": []
    },
    {
      "Translate": {
        "X": 203.25,
        "Y": -7.5,
        "Z": -0.75
      },
      "Actor name": "TagLightActor",
      "Actor params": [
        36,
        33,
        false,
        1.0
      ],
      "Conditions": []
    },
    {
      "Translate": {
        "X": 196.5,
        "Y": -18.0,
        "Z": -0.75
      },
      "Actor name": "TagLightActor",
      "Actor params": [
        37,
        34,
        false,
        1.0
      ],
      "Conditions": []
    },
    {
      "Translate": {
        "X": 228.0,
        "Y": -18.0,
        "Z": -0.75
      },
      "Actor name": "TagLightActor",
      "Actor params": [
        38,
        35,
        false,
        1.0
      ],
      "Conditions": []
    }
  ],
  "ActorParams": [
    "S104_R001_Start",
    "AreaStartCommon:WalkIn",
    null,
    "",
    0.0,
    "S104_R001_WarpBoss",
    "AreaStartCommon:MidBossWarpIn",
    "S110_R004_Start",
    "AreaStartCommon:TopWallLadderUpIn",
    "S110_R006_Start",
    "AreaStartCommon:LadderDown",
    "Wall",
    "S_Dungeon104_001_Effect_00",
    "S_Dungeon104_001",
    0,
    1,
    "Field",
    "Field_Jungle_008",
    "AreaExitCommon:WalkOut",
    "true",
    197,
    false,
    "S_Dungeon104_002_Effect_00",
    "S_Dungeon104_002",
    2,
    "S_Dungeon104_003_Effect_00",
    "S_Dungeon104_003",
    "Large__MI_SpiderWeb_00",
    "S_Dungeon104_004_Effect_00",
    "S_Dungeon104_004",
    3,
    "FloorChangeCommon:TopLadderDown",
    "None",
    "S_Dungeon104_006_Effect_00",
    "TagTailorPlayer_Lamp_Wall_Side_00_SD104",
    "S_Dungeon104_006",
    "FloorChangeCommon:LadderUp",
    1.5,
    15,
    "S_Dungeon104_007_Effect_00",
    "S_Dungeon104_007",
    "S_Dungeon104_009_Effect_00",
    "S_Dungeon104_009",
    "S_Dungeon104_010",
    "S_Dungeon104_010_Effect_00",
    "EvF_BalomLv2Dead",
    "BalomPiece0",
    "BalomPiece1",
    "BalomPiece2",
    "BalomPiece3",
    "BalomPiece4",
    "Switch0",
    29,
    16,
    4,
    1.0,
    5,
    6,
    7,
    8,
    9,
    10,
    11,
    12,
    13,
    14,
    17,
    18,
    19,
    20,
    21,
    22,
    23,
    24,
    25,
    26,
    27,
    28,
    30,
    31,
    32,
    33,
    34,
    35,
    36,
    37,
    38
  ]
}