{
  "FileName": "HylianF018",
  "Version": "0.3.0.0",
  "Flowcharts": {
    "HylianF018": {
      "Name": "HylianF018",
      "Actors": [
        {
          "Name": "HylianF018",
          "SecondaryName": "",
          "ArgumentName": "",
          "EntryPointIndex": -1,
          "CutNumber": 1,
          "Actions": [
            "Talk",
            "TalkKeep",
            "SetInstanceVariableBool",
            "GenericTalkSequenceWithDialog",
            "PlayAnimationNoWait",
            "SetFacialExpression"
          ],
          "Queries": [
            "GetInstanceVariableBool"
          ],
          "Parameters": {}
        },
        {
          "Name": "Dialog",
          "SecondaryName": "",
          "ArgumentName": "",
          "EntryPointIndex": -1,
          "CutNumber": 1,
          "Actions": [],
          "Queries": [
            "GetLastResult4"
          ],
          "Parameters": {}
        },
        {
          "Name": "ShopUI",
          "SecondaryName": "",
          "ArgumentName": "",
          "EntryPointIndex": -1,
          "CutNumber": 1,
          "Actions": [
            "ShowSell"
          ],
          "Queries": [],
          "Parameters": {}
        },
        {
          "Name": "Player",
          "SecondaryName": "",
          "ArgumentName": "",
          "EntryPointIndex": -1,
          "CutNumber": 1,
          "Actions": [],
          "Queries": [
            "HasSellableItems"
          ],
          "Parameters": {}
        }
      ],
      "Events": [
        {
          "NextEventIndex": -1,
          "ActorIndex": 0,
          "ActorActionIndex": 0,
          "Parameters": {
            "getAttention": {
              "Bool": false
            },
            "message": {
              "String": "scenario/HylianGeneralTalk:HylianF018Talk020_010"
            }
          },
          "ActorName": "HylianF018",
          "Name": "Event0",
          "Type": "Action"
        },
        {
          "NextEventIndex": 6,
          "ActorIndex": 0,
          "ActorActionIndex": 0,
          "Parameters": {
            "getAttention": {
              "Bool": false
            },
            "message": {
              "String": "scenario/HylianGeneralTalk:HylianF018Talk010_010"
            }
          },
          "NextEventName": "Event24",
          "ActorName": "HylianF018",
          "Name": "Event3",
          "Type": "Action"
        },
        {
          "NextEventIndex": -1,
          "ActorIndex": 0,
          "ActorActionIndex": 1,
          "Parameters": {
            "getAttention": {
              "Bool": false
            },
            "message": {
              "String": "scenario/HylianGeneralTalk:HylianF018Talk010_020"
            }
          },
          "ActorName": "HylianF018",
          "Name": "Event4",
          "Type": "Action"
        },
        {
          "NextEventIndex": -1,
          "ActorIndex": 0,
          "ActorActionIndex": 0,
          "Parameters": {
            "getAttention": {
              "Bool": false
            },
            "message": {
              "String": "scenario/HylianGeneralTalk:HylianF018Talk030_010"
            }
          },
          "ActorName": "HylianF018",
          "Name": "Event11",
          "Type": "Action"
        },
        {
          "NextEventIndex": -1,
          "ActorIndex": 0,
          "ActorActionIndex": 0,
          "Parameters": {
            "getAttention": {
              "Bool": false
            },
            "message": {
              "String": "scenario/HylianGeneralTalk:HylianF018Talk010_020"
            }
          },
          "ActorName": "HylianF018",
          "Name": "Event20",
          "Type": "Action"
        },
        {
          "ActorIndex": 0,
          "ActorQueryIndex": 0,
          "Parameters": {
            "name": {
              "String": "talk010"
            }
          },
          "SwitchCases": [
            {
              "Value": 0,
              "EventIndex": 39
            },
            {
              "Value": 1,
              "EventIndex": 40
            }
          ],
          "ActorName": "HylianF018",
          "Name": "Event22",
          "Type": "Switch"
        },
        {
          "NextEventIndex": 38,
          "ActorIndex": 0,
          "ActorActionIndex": 2,
          "Parameters": {
            "name": {
              "String": "talk010"
            },
            "value": {
              "Bool": true
            }
          },
          "NextEventName": "Event38",
          "ActorName": "HylianF018",
          "Name": "Event24",
          "Type": "Action"
        },
        {
          "ActorIndex": 1,
          "ActorQueryIndex": 0,
          "Parameters": {
            "resultOnSkip": {
              "Int": 3
            }
          },
          "SwitchCases": [
            {
              "Value": 0,
              "EventIndex": 12
            },
            {
              "Value": 1,
              "EventIndex": 5
            },
            {
              "Value": 2,
              "EventIndex": 17
            }
          ],
          "ActorName": "Dialog",
          "Name": "Event1",
          "Type": "Switch"
        },
        {
          "NextEventIndex": -1,
          "ActorIndex": 0,
          "ActorActionIndex": 0,
          "Parameters": {
            "getAttention": {
              "Bool": false
            },
            "message": {
              "String": "ShopKeeperTalk:SeasideVillage_SellComp_010"
            }
          },
          "ActorName": "HylianF018",
          "Name": "Event5",
          "Type": "Action"
        },
        {
          "NextEventIndex": 7,
          "ActorIndex": 0,
          "ActorActionIndex": 3,
          "Parameters": {
            "absorbAllPastedActors": {
              "Bool": true
            },
            "aimFromPlayer": {
              "Bool": true
            },
            "aimToPlayer": {
              "Bool": true
            },
            "cameraLookAt": {
              "Bool": true
            },
            "destroyCarriedActor": {
              "Bool": true
            },
            "destroyProjectiles": {
              "Bool": true
            },
            "disableSyncRodBallFollow": {
              "Bool": true
            },
            "distanceOffset": {
              "Float": 0
            },
            "facial": {
              "String": ""
            },
            "hideItems": {
              "Bool": true
            },
            "isExcludeLocked": {
              "Bool": false
            },
            "keepPersonalSpace": {
              "Bool": true
            },
            "keepTalk": {
              "Bool": false
            },
            "lookAtOffsetX": {
              "Float": 0
            },
            "lookAtOffsetY": {
              "Float": 0
            },
            "lookAtOffsetZ": {
              "Float": 0
            },
            "message": {
              "String": "ShopKeeperTalk:SeasideVillage_SellCheck_010"
            },
            "playerTalkAnim": {
              "Bool": false
            },
            "playerTalkAnimName": {
              "String": ""
            },
            "resetOverlappedActorsOnMoveDone": {
              "Bool": true
            },
            "selfTalkAnim": {
              "Bool": true
            },
            "selfTalkAnimName": {
              "String": ""
            },
            "stopBuffEffect": {
              "Bool": true
            },
            "stopBurnEffect": {
              "Bool": true
            },
            "throughObstaclesOnMove": {
              "Bool": true
            },
            "unburrow": {
              "Bool": true
            },
            "unmorph": {
              "Bool": true
            },
            "unsync": {
              "Bool": true
            }
          },
          "NextEventName": "Event1",
          "ActorName": "HylianF018",
          "Name": "Event6",
          "Type": "Action"
        },
        {
          "NextEventIndex": 18,
          "ActorIndex": 0,
          "ActorActionIndex": 3,
          "Parameters": {
            "absorbAllPastedActors": {
              "Bool": true
            },
            "aimFromPlayer": {
              "Bool": true
            },
            "aimToPlayer": {
              "Bool": true
            },
            "cameraLookAt": {
              "Bool": true
            },
            "destroyCarriedActor": {
              "Bool": true
            },
            "destroyProjectiles": {
              "Bool": true
            },
            "disableSyncRodBallFollow": {
              "Bool": true
            },
            "distanceOffset": {
              "Float": 0
            },
            "facial": {
              "String": ""
            },
            "hideItems": {
              "Bool": true
            },
            "isExcludeLocked": {
              "Bool": false
            },
            "keepPersonalSpace": {
              "Bool": true
            },
            "keepTalk": {
              "Bool": false
            },
            "lookAtOffsetX": {
              "Float": 0
            },
            "lookAtOffsetY": {
              "Float": 0
            },
            "lookAtOffsetZ": {
              "Float": 0
            },
            "message": {
              "String": "ShopKeeperTalk:SeasideVillage_SellCheck_010"
            },
            "playerTalkAnim": {
              "Bool": false
            },
            "playerTalkAnimName": {
              "String": ""
            },
            "resetOverlappedActorsOnMoveDone": {
              "Bool": true
            },
            "selfTalkAnim": {
              "Bool": true
            },
            "selfTalkAnimName": {
              "String": ""
            },
            "stopBuffEffect": {
              "Bool": true
            },
            "stopBurnEffect": {
              "Bool": true
            },
            "throughObstaclesOnMove": {
              "Bool": true
            },
            "unburrow": {
              "Bool": true
            },
            "unmorph": {
              "Bool": true
            },
            "unsync": {
              "Bool": true
            }
          },
          "NextEventName": "Event7",
          "ActorName": "HylianF018",
          "Name": "Event10",
          "Type": "Action"
        },
        {
          "NextEventIndex": 23,
          "ActorIndex": 0,
          "ActorActionIndex": 3,
          "Parameters": {
            "absorbAllPastedActors": {
              "Bool": true
            },
            "aimFromPlayer": {
              "Bool": true
            },
            "aimToPlayer": {
              "Bool": true
            },
            "cameraLookAt": {
              "Bool": true
            },
            "destroyCarriedActor": {
              "Bool": true
            },
            "destroyProjectiles": {
              "Bool": true
            },
            "disableSyncRodBallFollow": {
              "Bool": true
            },
            "distanceOffset": {
              "Float": 0
            },
            "facial": {
              "String": ""
            },
            "hideItems": {
              "Bool": true
            },
            "isExcludeLocked": {
              "Bool": false
            },
            "keepPersonalSpace": {
              "Bool": true
            },
            "keepTalk": {
              "Bool": false
            },
            "lookAtOffsetX": {
              "Float": 0
            },
            "lookAtOffsetY": {
              "Float": 0
            },
            "lookAtOffsetZ": {
              "Float": 0
            },
            "message": {
              "String": "ShopKeeperTalk:SeasideVillage_SellCheck_010"
            },
            "playerTalkAnim": {
              "Bool": false
            },
            "playerTalkAnimName": {
              "String": ""
            },
            "resetOverlappedActorsOnMoveDone": {
              "Bool": true
            },
            "selfTalkAnim": {
              "Bool": true
            },
            "selfTalkAnimName": {
              "String": ""
            },
            "stopBuffEffect": {
              "Bool": true
            },
            "stopBurnEffect": {
              "Bool": true
            },
            "throughObstaclesOnMove": {
              "Bool": true
            },
            "unburrow": {
              "Bool": true
            },
            "unmorph": {
              "Bool": true
            },
            "unsync": {
              "Bool": true
            }
          },
          "NextEventName": "Event2",
          "ActorName": "HylianF018",
          "Name": "Event15",
          "Type": "Action"
        },
        {
          "ActorIndex": 3,
          "ActorQueryIndex": 0,
          "SwitchCases": [
            {
              "Value": 0,
              "EventIndex": 37
            },
            {
              "Value": 1,
              "EventIndex": 14
            }
          ],
          "ActorName": "Player",
          "Name": "Event16",
          "Type": "Switch"
        },
        {
          "NextEventIndex": -1,
          "ActorIndex": 0,
          "ActorActionIndex": 0,
          "Parameters": {
            "getAttention": {
              "Bool": false
            },
            "message": {
              "String": "ShopKeeperTalk:SeasideVillage_NotHaveItem_010"
            }
          },
          "ActorName": "HylianF018",
          "Name": "Event17",
          "Type": "Action"
        },
        {
          "NextEventIndex": 8,
          "ActorIndex": 2,
          "ActorActionIndex": 0,
          "Parameters": {
            "choose": {
              "String": "ShopKeeperTalk:SeasideVillage_ChooseSell_010"
            },
            "confirm": {
              "String": "ShopKeeperTalk:SeasideVillage_SellConfirm_010"
            },
            "howMany": {
              "String": "ShopKeeperTalk:SeasideVillage_HowManySell_010"
            },
            "multipleConfirm": {
              "String": "ShopKeeperTalk:SeasideVillage_SellConfirm_010"
            },
            "sold": {
              "String": "ShopKeeperTalk:SeasideVillage_Sold_010"
            }
          },
          "NextEventName": "Event5",
          "ActorName": "ShopUI",
          "Name": "Event18",
          "Type": "Action"
        },
        {
          "NextEventIndex": -1,
          "ActorIndex": 0,
          "ActorActionIndex": 0,
          "Parameters": {
            "getAttention": {
              "Bool": false
            },
            "message": {
              "String": "scenario/HylianGeneralTalk:HylianF018Talk040_010"
            }
          },
          "ActorName": "HylianF018",
          "Name": "Event14",
          "Type": "Action"
        },
        {
          "NextEventIndex": 28,
          "ActorIndex": 0,
          "ActorActionIndex": 3,
          "Parameters": {
            "absorbAllPastedActors": {
              "Bool": true
            },
            "aimFromPlayer": {
              "Bool": true
            },
            "aimToPlayer": {
              "Bool": true
            },
            "cameraLookAt": {
              "Bool": true
            },
            "destroyCarriedActor": {
              "Bool": true
            },
            "destroyProjectiles": {
              "Bool": true
            },
            "disableSyncRodBallFollow": {
              "Bool": true
            },
            "distanceOffset": {
              "Float": 0
            },
            "facial": {
              "String": ""
            },
            "hideItems": {
              "Bool": true
            },
            "isExcludeLocked": {
              "Bool": false
            },
            "keepPersonalSpace": {
              "Bool": true
            },
            "keepTalk": {
              "Bool": false
            },
            "lookAtOffsetX": {
              "Float": 0
            },
            "lookAtOffsetY": {
              "Float": 0
            },
            "lookAtOffsetZ": {
              "Float": 0
            },
            "message": {
              "String": "ShopKeeperTalk:SeasideVillage_SellCheck_010"
            },
            "playerTalkAnim": {
              "Bool": false
            },
            "playerTalkAnimName": {
              "String": ""
            },
            "resetOverlappedActorsOnMoveDone": {
              "Bool": true
            },
            "selfTalkAnim": {
              "Bool": true
            },
            "selfTalkAnimName": {
              "String": ""
            },
            "stopBuffEffect": {
              "Bool": true
            },
            "stopBurnEffect": {
              "Bool": true
            },
            "throughObstaclesOnMove": {
              "Bool": true
            },
            "unburrow": {
              "Bool": true
            },
            "unmorph": {
              "Bool": true
            },
            "unsync": {
              "Bool": true
            }
          },
          "NextEventName": "Event21",
          "ActorName": "HylianF018",
          "Name": "Event27",
          "Type": "Action"
        },
        {
          "NextEventIndex": -1,
          "ActorIndex": 0,
          "ActorActionIndex": 0,
          "Parameters": {
            "getAttention": {
              "Bool": false
            },
            "message": {
              "String": "ShopKeeperTalk:SeasideVillage_SellCheckBye_010"
            }
          },
          "ActorName": "HylianF018",
          "Name": "Event32",
          "Type": "Action"
        },
        {
          "ActorIndex": 1,
          "ActorQueryIndex": 0,
          "Parameters": {
            "resultOnSkip": {
              "Int": 3
            }
          },
          "SwitchCases": [
            {
              "Value": 0,
              "EventIndex": 20
            },
            {
              "Value": 1,
              "EventIndex": 43
            },
            {
              "Value": 2,
              "EventIndex": 22
            }
          ],
          "ActorName": "Dialog",
          "Name": "Event7",
          "Type": "Switch"
        },
        {
          "NextEventIndex": -1,
          "ActorIndex": 0,
          "ActorActionIndex": 0,
          "Parameters": {
            "getAttention": {
              "Bool": false
            },
            "message": {
              "String": "ShopKeeperTalk:SeasideVillage_SellComp_010"
            }
          },
          "ActorName": "HylianF018",
          "Name": "Event33",
          "Type": "Action"
        },
        {
          "ActorIndex": 3,
          "ActorQueryIndex": 0,
          "SwitchCases": [
            {
              "Value": 0,
              "EventIndex": 42
            },
            {
              "Value": 1,
              "EventIndex": 33
            }
          ],
          "ActorName": "Player",
          "Name": "Event34",
          "Type": "Switch"
        },
        {
          "NextEventIndex": -1,
          "ActorIndex": 0,
          "ActorActionIndex": 0,
          "Parameters": {
            "getAttention": {
              "Bool": false
            },
            "message": {
              "String": "ShopKeeperTalk:SeasideVillage_NotHaveItem_010"
            }
          },
          "ActorName": "HylianF018",
          "Name": "Event35",
          "Type": "Action"
        },
        {
          "NextEventIndex": -1,
          "ActorIndex": 0,
          "ActorActionIndex": 0,
          "Parameters": {
            "getAttention": {
              "Bool": false
            },
            "message": {
              "String": "ShopKeeperTalk:SeasideVillage_SellCheckBye_010"
            }
          },
          "ActorName": "HylianF018",
          "Name": "Event37",
          "Type": "Action"
        },
        {
          "ActorIndex": 1,
          "ActorQueryIndex": 0,
          "Parameters": {
            "resultOnSkip": {
              "Int": 3
            }
          },
          "SwitchCases": [
            {
              "Value": 0,
              "EventIndex": 25
            },
            {
              "Value": 1,
              "EventIndex": 3
            },
            {
              "Value": 2,
              "EventIndex": 27
            }
          ],
          "ActorName": "Dialog",
          "Name": "Event2",
          "Type": "Switch"
        },
        {
          "NextEventIndex": -1,
          "ActorIndex": 0,
          "ActorActionIndex": 0,
          "Parameters": {
            "getAttention": {
              "Bool": false
            },
            "message": {
              "String": "ShopKeeperTalk:SeasideVillage_SellComp_010"
            }
          },
          "ActorName": "HylianF018",
          "Name": "Event8",
          "Type": "Action"
        },
        {
          "ActorIndex": 3,
          "ActorQueryIndex": 0,
          "SwitchCases": [
            {
              "Value": 0,
              "EventIndex": 45
            },
            {
              "Value": 1,
              "EventIndex": 34
            }
          ],
          "ActorName": "Player",
          "Name": "Event9",
          "Type": "Switch"
        },
        {
          "NextEventIndex": -1,
          "ActorIndex": 0,
          "ActorActionIndex": 0,
          "Parameters": {
            "getAttention": {
              "Bool": false
            },
            "message": {
              "String": "ShopKeeperTalk:SeasideVillage_NotHaveItem_010"
            }
          },
          "ActorName": "HylianF018",
          "Name": "Event12",
          "Type": "Action"
        },
        {
          "NextEventIndex": -1,
          "ActorIndex": 0,
          "ActorActionIndex": 0,
          "Parameters": {
            "getAttention": {
              "Bool": false
            },
            "message": {
              "String": "ShopKeeperTalk:SeasideVillage_SellCheckBye_010"
            }
          },
          "ActorName": "HylianF018",
          "Name": "Event19",
          "Type": "Action"
        },
        {
          "ActorIndex": 1,
          "ActorQueryIndex": 0,
          "Parameters": {
            "resultOnSkip": {
              "Int": 3
            }
          },
          "SwitchCases": [
            {
              "Value": 0,
              "EventIndex": 30
            },
            {
              "Value": 1,
              "EventIndex": 15
            },
            {
              "Value": 2,
              "EventIndex": 32
            }
          ],
          "ActorName": "Dialog",
          "Name": "Event21",
          "Type": "Switch"
        },
        {
          "NextEventIndex": -1,
          "ActorIndex": 0,
          "ActorActionIndex": 0,
          "Parameters": {
            "getAttention": {
              "Bool": false
            },
            "message": {
              "String": "ShopKeeperTalk:SeasideVillage_SellComp_010"
            }
          },
          "ActorName": "HylianF018",
          "Name": "Event23",
          "Type": "Action"
        },
        {
          "ActorIndex": 3,
          "ActorQueryIndex": 0,
          "SwitchCases": [
            {
              "Value": 0,
              "EventIndex": 47
            },
            {
              "Value": 1,
              "EventIndex": 35
            }
          ],
          "ActorName": "Player",
          "Name": "Event25",
          "Type": "Switch"
        },
        {
          "NextEventIndex": -1,
          "ActorIndex": 0,
          "ActorActionIndex": 0,
          "Parameters": {
            "getAttention": {
              "Bool": false
            },
            "message": {
              "String": "ShopKeeperTalk:SeasideVillage_NotHaveItem_010"
            }
          },
          "ActorName": "HylianF018",
          "Name": "Event26",
          "Type": "Action"
        },
        {
          "NextEventIndex": -1,
          "ActorIndex": 0,
          "ActorActionIndex": 0,
          "Parameters": {
            "getAttention": {
              "Bool": false
            },
            "message": {
              "String": "ShopKeeperTalk:SeasideVillage_SellCheckBye_010"
            }
          },
          "ActorName": "HylianF018",
          "Name": "Event29",
          "Type": "Action"
        },
        {
          "NextEventIndex": 19,
          "ActorIndex": 2,
          "ActorActionIndex": 0,
          "Parameters": {
            "choose": {
              "String": "ShopKeeperTalk:SeasideVillage_ChooseSell_010"
            },
            "confirm": {
              "String": "ShopKeeperTalk:SeasideVillage_SellConfirm_010"
            },
            "howMany": {
              "String": "ShopKeeperTalk:SeasideVillage_HowManySell_010"
            },
            "multipleConfirm": {
              "String": "ShopKeeperTalk:SeasideVillage_SellConfirm_010"
            },
            "sold": {
              "String": "ShopKeeperTalk:SeasideVillage_Sold_010"
            }
          },
          "NextEventName": "Event33",
          "ActorName": "ShopUI",
          "Name": "Event30",
          "Type": "Action"
        },
        {
          "NextEventIndex": 24,
          "ActorIndex": 2,
          "ActorActionIndex": 0,
          "Parameters": {
            "choose": {
              "String": "ShopKeeperTalk:SeasideVillage_ChooseSell_010"
            },
            "confirm": {
              "String": "ShopKeeperTalk:SeasideVillage_SellConfirm_010"
            },
            "howMany": {
              "String": "ShopKeeperTalk:SeasideVillage_HowManySell_010"
            },
            "multipleConfirm": {
              "String": "ShopKeeperTalk:SeasideVillage_SellConfirm_010"
            },
            "sold": {
              "String": "ShopKeeperTalk:SeasideVillage_Sold_010"
            }
          },
          "NextEventName": "Event8",
          "ActorName": "ShopUI",
          "Name": "Event13",
          "Type": "Action"
        },
        {
          "NextEventIndex": 29,
          "ActorIndex": 2,
          "ActorActionIndex": 0,
          "Parameters": {
            "choose": {
              "String": "ShopKeeperTalk:SeasideVillage_ChooseSell_010"
            },
            "confirm": {
              "String": "ShopKeeperTalk:SeasideVillage_SellConfirm_010"
            },
            "howMany": {
              "String": "ShopKeeperTalk:SeasideVillage_HowManySell_010"
            },
            "multipleConfirm": {
              "String": "ShopKeeperTalk:SeasideVillage_SellConfirm_010"
            },
            "sold": {
              "String": "ShopKeeperTalk:SeasideVillage_Sold_010"
            }
          },
          "NextEventName": "Event23",
          "ActorName": "ShopUI",
          "Name": "Event28",
          "Type": "Action"
        },
        {
          "NextEventIndex": 13,
          "ActorIndex": 0,
          "ActorActionIndex": 4,
          "Parameters": {
            "blendFrame": {
              "Int": -1
            },
            "layer": {
              "Int": 0
            },
            "name": {
              "String": "no01,wait01"
            },
            "restart": {
              "Bool": false
            }
          },
          "NextEventName": "Event17",
          "ActorName": "HylianF018",
          "Name": "Event31",
          "Type": "Action"
        },
        {
          "NextEventIndex": 36,
          "ActorIndex": 0,
          "ActorActionIndex": 5,
          "Parameters": {
            "expression": {
              "String": "sad"
            }
          },
          "NextEventName": "Event31",
          "ActorName": "HylianF018",
          "Name": "Event36",
          "Type": "Action"
        },
        {
          "NextEventIndex": 2,
          "ActorIndex": 0,
          "ActorActionIndex": 5,
          "Parameters": {
            "expression": {
              "String": "sad"
            }
          },
          "NextEventName": "Event4",
          "ActorName": "HylianF018",
          "Name": "Event38",
          "Type": "Action"
        },
        {
          "NextEventIndex": 1,
          "ActorIndex": 0,
          "ActorActionIndex": 5,
          "Parameters": {
            "expression": {
              "String": "smile"
            }
          },
          "NextEventName": "Event3",
          "ActorName": "HylianF018",
          "Name": "Event39",
          "Type": "Action"
        },
        {
          "NextEventIndex": 4,
          "ActorIndex": 0,
          "ActorActionIndex": 5,
          "Parameters": {
            "expression": {
              "String": "sad"
            }
          },
          "NextEventName": "Event20",
          "ActorName": "HylianF018",
          "Name": "Event40",
          "Type": "Action"
        },
        {
          "NextEventIndex": 21,
          "ActorIndex": 0,
          "ActorActionIndex": 4,
          "Parameters": {
            "blendFrame": {
              "Int": -1
            },
            "layer": {
              "Int": 0
            },
            "name": {
              "String": "no01,wait01"
            },
            "restart": {
              "Bool": false
            }
          },
          "NextEventName": "Event35",
          "ActorName": "HylianF018",
          "Name": "Event41",
          "Type": "Action"
        },
        {
          "NextEventIndex": 41,
          "ActorIndex": 0,
          "ActorActionIndex": 5,
          "Parameters": {
            "expression": {
              "String": "sad"
            }
          },
          "NextEventName": "Event41",
          "ActorName": "HylianF018",
          "Name": "Event42",
          "Type": "Action"
        },
        {
          "NextEventIndex": 48,
          "ActorIndex": 0,
          "ActorActionIndex": 5,
          "Parameters": {
            "expression": {
              "String": "sad"
            }
          },
          "NextEventName": "Event49",
          "ActorName": "HylianF018",
          "Name": "Event43",
          "Type": "Action"
        },
        {
          "NextEventIndex": 26,
          "ActorIndex": 0,
          "ActorActionIndex": 4,
          "Parameters": {
            "blendFrame": {
              "Int": -1
            },
            "layer": {
              "Int": 0
            },
            "name": {
              "String": "no01,wait01"
            },
            "restart": {
              "Bool": false
            }
          },
          "NextEventName": "Event12",
          "ActorName": "HylianF018",
          "Name": "Event44",
          "Type": "Action"
        },
        {
          "NextEventIndex": 44,
          "ActorIndex": 0,
          "ActorActionIndex": 5,
          "Parameters": {
            "expression": {
              "String": "sad"
            }
          },
          "NextEventName": "Event44",
          "ActorName": "HylianF018",
          "Name": "Event45",
          "Type": "Action"
        },
        {
          "NextEventIndex": 31,
          "ActorIndex": 0,
          "ActorActionIndex": 4,
          "Parameters": {
            "blendFrame": {
              "Int": -1
            },
            "layer": {
              "Int": 0
            },
            "name": {
              "String": "no01,wait01"
            },
            "restart": {
              "Bool": false
            }
          },
          "NextEventName": "Event26",
          "ActorName": "HylianF018",
          "Name": "Event46",
          "Type": "Action"
        },
        {
          "NextEventIndex": 46,
          "ActorIndex": 0,
          "ActorActionIndex": 5,
          "Parameters": {
            "expression": {
              "String": "sad"
            }
          },
          "NextEventName": "Event46",
          "ActorName": "HylianF018",
          "Name": "Event47",
          "Type": "Action"
        },
        {
          "NextEventIndex": 0,
          "ActorIndex": 0,
          "ActorActionIndex": 4,
          "Parameters": {
            "blendFrame": {
              "Int": 15
            },
            "layer": {
              "Int": 0
            },
            "name": {
              "String": "wait30"
            },
            "restart": {
              "Bool": false
            }
          },
          "NextEventName": "Event0",
          "ActorName": "HylianF018",
          "Name": "Event49",
          "Type": "Action"
        }
      ],
      "EntryPoints": {
        "talk010": {
          "SubFlowEventIndices": [],
          "EventIndex": 9
        },
        "talk020": {
          "SubFlowEventIndices": [],
          "EventIndex": 10
        },
        "talk030": {
          "SubFlowEventIndices": [],
          "EventIndex": 11
        },
        "talk040": {
          "SubFlowEventIndices": [],
          "EventIndex": 16
        }
      }
    }
  },
  "Timelines": {}
}